.gitignore
LICENSE
MANIFEST.in
README
RELEASE-VERSION
TODO
rtsptogo.conf
setup.py
version.py
rtsptogo/__init__.py
rtsptogo/config.py
rtsptogo/discover.py
rtsptogo/main.py
rtsptogo/rtp.py
rtsptogo/rtspd.py
rtsptogo/tivoapi.py
rtsptogo/web_app.py
rtsptogo/zeroconf.py
rtsptogo.egg-info/PKG-INFO
rtsptogo.egg-info/SOURCES.txt
rtsptogo.egg-info/dependency_links.txt
rtsptogo.egg-info/entry_points.txt
rtsptogo.egg-info/requires.txt
rtsptogo.egg-info/top_level.txt
rtsptogo/templates/index.html
rtsptogo/templates/listing.html