Metadata-Version: 1.0
Name: rtsptogo
Version: 0.1.4dev2
Summary: rtsptogo is a tivo togo proxy serving mp4 video over RSTP
Home-page: http://github.com/armooo/rtsptogo/
Author: Jason Michalski
Author-email: armooo@armooo.net
License: GPL
Keywords: tivo rstp mobile
Platform: UNKNOWN
Classifier: Programming Language :: Python
Classifier: Intended Audience :: End Users/Desktop
Classifier: License :: OSI Approved :: GNU General Public License (GPL)
Classifier: Topic :: Internet
Classifier: Topic :: Multimedia :: Video :: Conversion
